pywaffle/__init__.py
pywaffle/fontawesome_handler.py
pywaffle/fontawesome_mapping.py
pywaffle/waffle.py
pywaffle-1.1.1.dist-info/LICENSE
pywaffle-1.1.1.dist-info/METADATA
pywaffle-1.1.1.dist-info/WHEEL
pywaffle-1.1.1.dist-info/top_level.txt
pywaffle-1.1.1.dist-info/RECORD
